terraria_pc_xbox360_player_converter
