Metadata-Version: 2.1
Name: terraria-pc-xbox360-player-converter
Version: 1.0.2
Summary: Library for converting between TerrariaPCPlayer and TerrariaXbox360Player
Home-page: https://gitlab.com/terraria-converters/terraria-pc-xbox360-player-converter
Author: Filip K
Author-email: fkwilczek@gmail.com
License: GNU General Public License v3 (GPLv3)
Classifier: Programming Language :: Python :: 3
Classifier: Operating System :: OS Independent
Classifier: License :: OSI Approved :: GNU General Public License v3 (GPLv3)
License-File: LICENSE
